modelscout/__init__.py
modelscout/cli.py
modelscout/engine.py
modelscout/models.csv
modelscout-0.1.1.dist-info/METADATA
modelscout-0.1.1.dist-info/WHEEL
modelscout-0.1.1.dist-info/entry_points.txt
modelscout-0.1.1.dist-info/top_level.txt
modelscout-0.1.1.dist-info/RECORD
