Metadata-Version: 2.2
Name: modelscout
Version: 0.1.1
Summary: ModelScout: Find the best LLM for your needs.
Home-page: https://github.com/Hadi-M-Ibrahim/ModelScout
Author: Hadi Ibrahim
Classifier: Programming Language :: Python :: 3
Classifier: License :: OSI Approved :: MIT License
Classifier: Operating System :: OS Independent
Requires-Python: >=3.7
Requires-Dist: pandas>=1.0.0
Requires-Dist: numpy>=1.18.0
Dynamic: author
Dynamic: classifier
Dynamic: description
Dynamic: description-content-type
Dynamic: home-page
Dynamic: requires-dist
Dynamic: requires-python
Dynamic: summary
